rtos_cli/__init__.py
rtos_cli/rtos_cli.py
rtos_cli/commands/__init__.py
rtos_cli/commands/add_hal.py
rtos_cli/commands/create_hal.py
rtos_cli/commands/create_hal_i2c.py
rtos_cli/commands/create_lib.py
rtos_cli/commands/create_msg.py
rtos_cli/commands/create_project.py
rtos_cli/commands/create_task.py
rtos_cli/commands/create_topic.py
rtos_cli/commands/generate_docs.py
rtos_cli/commands/init_project.py
rtos_cli/commands/view_graph.py
rtos_cli/templates/.gitignore
rtos_cli/templates/platformio.ini
rtos_cli/templates/hal/hal_ble.template
rtos_cli/templates/hal/hal_gpio.template
rtos_cli/templates/hal/hal_i2c.template
rtos_cli/templates/hal/hal_pwm.template
rtos_cli/templates/hal/hal_rtc.template
rtos_cli/templates/hal/hal_sd.template
rtos_cli/templates/hal/hal_spi.template
rtos_cli/templates/hal/hal_timer.template
rtos_cli/templates/hal/hal_uart.template
rtos_cli/templates/hal/hal_wifi.template
rtos_cli/templates/include/README.md
rtos_cli/templates/include/project_config.h
rtos_cli/templates/lib/README.md
rtos_cli/templates/lib/message/library.json
rtos_cli/templates/lib/message/std_msgs.cpp
rtos_cli/templates/lib/message/std_msgs.h
rtos_cli/templates/src/main.cpp
rtos_cli/templates/test/README.md
rtos_cli/utils/__init__.py
rtos_cli/utils/create_topology.py
rtos_cli/utils/doxygen.py
rtos_cli/utils/doxygen_generator.py
rtos_cli/utils/file_utils.py
rtos_cli/utils/graph_builder.py
rtos_cli/utils/naming.py
rtos_cli/utils/project_paths.py
rtos_cli/utils/readme_updater.py
rtos_cli/utils/template_engine.py
rtos_cli/utils/yaml_loader.py
rtos_cli-2.0.2.dist-info/licenses/LICENSE
rtos_cli-2.0.2.dist-info/METADATA
rtos_cli-2.0.2.dist-info/WHEEL
rtos_cli-2.0.2.dist-info/entry_points.txt
rtos_cli-2.0.2.dist-info/top_level.txt
rtos_cli-2.0.2.dist-info/RECORD
