Metadata-Version: 2.4
Name: rtos_cli
Version: 2.0.2
Summary: CLI para automatizar proyectos PlatformIO con FreeRTOS en base a Framework Arduino y un ESP32
Home-page: https://github.com/efrainra7/rtos_cli
Author: Efrain Reyes Araujo
Author-email: dev@reyes-araujo.com
License: MIT
Classifier: Programming Language :: Python :: 3
Classifier: License :: OSI Approved :: MIT License
Classifier: Operating System :: OS Independent
Classifier: Development Status :: 4 - Beta
Classifier: Intended Audience :: Developers
Classifier: Topic :: Software Development :: Embedded Systems
Classifier: Topic :: Utilities
Requires-Python: >=3.7
License-File: LICENSE
Requires-Dist: pyyaml>=6.0
Requires-Dist: pydot>=4.0.0
Requires-Dist: networkx>=3.1
Requires-Dist: graphviz>=0.20.1
Dynamic: author
Dynamic: author-email
Dynamic: classifier
Dynamic: description
Dynamic: description-content-type
Dynamic: home-page
Dynamic: license
Dynamic: license-file
Dynamic: requires-dist
Dynamic: requires-python
Dynamic: summary
